.gitignore
LICENSE
README.md
setup.py
tox.ini
.github/workflows/tests.yml
freeze_room/__init__.py
freeze_room/_constants.py
synapse_freeze_room.egg-info/PKG-INFO
synapse_freeze_room.egg-info/SOURCES.txt
synapse_freeze_room.egg-info/dependency_links.txt
synapse_freeze_room.egg-info/requires.txt
synapse_freeze_room.egg-info/top_level.txt
tests/__init__.py
tests/test_room_freeze.py