Metadata-Version: 2.1
Name: synapse-freeze-room
Version: 1.1.0
Summary: A third-party rules module for Synapse to automatically freeze a room when the last admin leaves it and allow other members to unfreeze them and become the new admin.
Home-page: https://github.com/matrix-org/synapse-freeze-room
License: UNKNOWN
Platform: UNKNOWN
Classifier: Development Status :: 4 - Beta
Classifier: License :: OSI Approved :: Apache Software License
Classifier: Programming Language :: Python :: 3
Requires-Python: >=3.6
License-File: LICENSE
